pmpt_main.py
pmpt_cli-0.1.7.dist-info/licenses/LICENSE
src/__init__.py
src/cli.py
src/clipboard.py
src/config.py
src/language_detector.py
src/providers.py
src/version.py
pmpt_cli-0.1.7.dist-info/METADATA
pmpt_cli-0.1.7.dist-info/WHEEL
pmpt_cli-0.1.7.dist-info/entry_points.txt
pmpt_cli-0.1.7.dist-info/top_level.txt
pmpt_cli-0.1.7.dist-info/RECORD
